jcache/__init__.py
jcache-0.3.dist-info/LICENSE
jcache-0.3.dist-info/METADATA
jcache-0.3.dist-info/WHEEL
jcache-0.3.dist-info/top_level.txt
jcache-0.3.dist-info/RECORD
