Metadata-Version: 2.1
Name: jcache
Version: 0.3
Summary: a library that can cache the return of a function to avoid repeated computing
Home-page: https://github.com/JackonYang/jcache
Author: Jackon Yang
Author-email: i@jackon.me
License: MIT
Platform: UNKNOWN
